{
  "backup_date": "2025-10-23T12:57:51.170430",
  "categories": [
    {
      "id": 1,
      "name": "0. Grundlagen",
      "slug": "grundlagen",
      "icon": "🎓",
      "description": "Fundamentale Konzepte und Frameworks für erfolgreiches Trading und Investieren",
      "sort_order": 0,
      "is_active": true
    },
    {
      "id": 2,
      "name": "1. Fundamentalanalyse",
      "slug": "fundamentalanalyse",
      "icon": "📊",
      "description": "Bewertung von Unternehmen anhand ihrer Geschäftszahlen",
      "sort_order": 1,
      "is_active": true
    },
    {
      "id": 7,
      "name": "1. Trading-Grundlagen",
      "slug": "trading-grundlagen",
      "icon": "📊",
      "description": "Grundlegende Trading-Konzepte und -Strategien",
      "sort_order": 1,
      "is_active": true
    },
    {
      "id": 3,
      "name": "2. Technische Analyse",
      "slug": "technische-analyse",
      "icon": "📈",
      "description": "Chartanalyse und Trading-Strategien",
      "sort_order": 2,
      "is_active": true
    },
    {
      "id": 4,
      "name": "3. Risikomanagement",
      "slug": "risikomanagement",
      "icon": "🛡️",
      "description": "Kapitalschutz und Money Management",
      "sort_order": 3,
      "is_active": true
    },
    {
      "id": 5,
      "name": "4. Trading Psychologie",
      "slug": "trading-psychologie",
      "icon": "🧠",
      "description": "Mentale Aspekte des erfolgreichen Tradings",
      "sort_order": 4,
      "is_active": true
    },
    {
      "id": 6,
      "name": "5. Elite - System III",
      "slug": "elite-system-iii",
      "icon": "🏆",
      "description": "Elite-Level Trading-Strategien, Meta-Learning und Prozessoptimierung",
      "sort_order": 5,
      "is_active": true
    },
    {
      "id": 8,
      "name": "🆕 Neue Module",
      "slug": "neue-module",
      "icon": "🆕",
      "description": "Automatisch erkannte Module - Bitte in die richtige Kategorie verschieben",
      "sort_order": 999,
      "is_active": true
    }
  ],
  "subcategories": [
    {
      "id": 7,
      "category_id": 6,
      "name": "5.0 Intro",
      "slug": "intro",
      "description": null,
      "icon": "🚀",
      "sort_order": 0,
      "is_active": true
    },
    {
      "id": 1,
      "category_id": 2,
      "name": "1.1 Bilanzanalyse",
      "slug": "bilanzanalyse",
      "description": null,
      "icon": "📋",
      "sort_order": 1,
      "is_active": true
    },
    {
      "id": 3,
      "category_id": 3,
      "name": "2.1 Chart-Patterns",
      "slug": "chart-patterns",
      "description": null,
      "icon": "📊",
      "sort_order": 1,
      "is_active": true
    },
    {
      "id": 5,
      "category_id": 4,
      "name": "3.1 Position Sizing",
      "slug": "position-sizing",
      "description": null,
      "icon": "⚖️",
      "sort_order": 1,
      "is_active": true
    },
    {
      "id": 6,
      "category_id": 5,
      "name": "4.1 Emotionen kontrollieren",
      "slug": "emotionen",
      "description": null,
      "icon": "😌",
      "sort_order": 1,
      "is_active": true
    },
    {
      "id": 10,
      "category_id": 6,
      "name": "5.1 Trade-Vorbereitung",
      "slug": "51-trade-vorbereitung",
      "description": null,
      "icon": "📋",
      "sort_order": 1,
      "is_active": true
    },
    {
      "id": 11,
      "category_id": 3,
      "name": "2.1 Chart-Patterns",
      "slug": "21-chart-patterns",
      "description": null,
      "icon": "🎯",
      "sort_order": 1,
      "is_active": true
    },
    {
      "id": 2,
      "category_id": 2,
      "name": "1.2 Kennzahlen",
      "slug": "kennzahlen",
      "description": null,
      "icon": "🔢",
      "sort_order": 2,
      "is_active": true
    },
    {
      "id": 4,
      "category_id": 3,
      "name": "2.2 Indikatoren",
      "slug": "indikatoren",
      "description": null,
      "icon": "📉",
      "sort_order": 2,
      "is_active": true
    },
    {
      "id": 9,
      "category_id": 6,
      "name": "Trading Konzepte",
      "slug": "trading-konzepte",
      "description": null,
      "icon": "📋",
      "sort_order": 2,
      "is_active": true
    },
    {
      "id": 8,
      "category_id": 6,
      "name": "5.1 Metalearning & The Process",
      "slug": "metalearning-the-process",
      "description": null,
      "icon": "🧠",
      "sort_order": 101,
      "is_active": true
    }
  ],
  "modules": [
    {
      "id": 1,
      "category_id": 1,
      "subcategory_id": null,
      "title": "Bridgewater Quadranten Masterclass",
      "slug": "bridgewater-quadranten",
      "description": "Ray Dalios vollständiges Wirtschafts-Framework: Die vier \"Jahreszeiten\" der Wirtschaft verstehen und ein wetterbeständiges Portfolio aufbauen",
      "icon": "📊",
      "template_file": "bridgewater_quadranten_complete.html",
      "content_type": "html",
      "external_url": null,
      "is_published": true,
      "is_lead_magnet": false,
      "required_subscription_levels": [
        "premium",
        "elite"
      ],
      "estimated_duration": 90,
      "difficulty_level": "intermediate",
      "sort_order": 1
    },
    {
      "id": 3,
      "category_id": 2,
      "subcategory_id": 1,
      "title": "Balance Sheet Basics",
      "slug": "balance-sheet-basics",
      "description": "Grundlagen der Bilanzanalyse für Aktieninvestoren (KOSTENLOS)",
      "icon": "📋",
      "template_file": null,
      "content_type": "html",
      "external_url": null,
      "is_published": true,
      "is_lead_magnet": true,
      "required_subscription_levels": [],
      "estimated_duration": 45,
      "difficulty_level": "beginner",
      "sort_order": 1
    },
    {
      "id": 4,
      "category_id": 4,
      "subcategory_id": 5,
      "title": "Die 2% Regel",
      "slug": "zwei-prozent-regel",
      "description": "Grundlagen des Risikomanagements - Nie mehr als 2% pro Trade riskieren (KOSTENLOS)",
      "icon": "⚠️",
      "template_file": null,
      "content_type": "html",
      "external_url": null,
      "is_published": true,
      "is_lead_magnet": true,
      "required_subscription_levels": [],
      "estimated_duration": 30,
      "difficulty_level": "beginner",
      "sort_order": 1
    },
    {
      "id": 6,
      "category_id": 2,
      "subcategory_id": 2,
      "title": "KGV, KBV & Co.",
      "slug": "kgv-kbv-kennzahlen",
      "description": "Die wichtigsten Bewertungskennzahlen verstehen und anwenden",
      "icon": "🔢",
      "template_file": null,
      "content_type": "html",
      "external_url": null,
      "is_published": true,
      "is_lead_magnet": false,
      "required_subscription_levels": [
        "premium",
        "elite"
      ],
      "estimated_duration": 90,
      "difficulty_level": "intermediate",
      "sort_order": 1
    },
    {
      "id": 7,
      "category_id": 3,
      "subcategory_id": 4,
      "title": "Moving Averages Masterclass",
      "slug": "moving-averages",
      "description": "Gleitende Durchschnitte richtig nutzen - Von EMA bis Magic Line",
      "icon": "📉",
      "template_file": null,
      "content_type": "html",
      "external_url": null,
      "is_published": true,
      "is_lead_magnet": false,
      "required_subscription_levels": [
        "premium",
        "elite"
      ],
      "estimated_duration": 75,
      "difficulty_level": "intermediate",
      "sort_order": 1
    },
    {
      "id": 8,
      "category_id": 5,
      "subcategory_id": 6,
      "title": "Fear & Greed Mastery",
      "slug": "fear-greed-mastery",
      "description": "Marktpsychologie verstehen und für profitable Trades nutzen",
      "icon": "🧠",
      "template_file": null,
      "content_type": "html",
      "external_url": null,
      "is_published": true,
      "is_lead_magnet": false,
      "required_subscription_levels": [
        "elite"
      ],
      "estimated_duration": 60,
      "difficulty_level": "advanced",
      "sort_order": 1
    },
    {
      "id": 10,
      "category_id": 6,
      "subcategory_id": 8,
      "title": "Meta-Learning: Die Wissenschaft des effektiven Lernens",
      "slug": "meta-learning-quiz",
      "description": "Wie Lance Breitstein vom struggling Trader zum #1 Trader bei Trillium wurde - Lerne die Wissenschaft des effektiven Lernens mit interaktivem Quiz",
      "icon": "🧠",
      "template_file": "meta_learning_quiz.html",
      "content_type": "html",
      "external_url": null,
      "is_published": true,
      "is_lead_magnet": false,
      "required_subscription_levels": [
        "elite"
      ],
      "estimated_duration": 45,
      "difficulty_level": "advanced",
      "sort_order": 1
    },
    {
      "id": 11,
      "category_id": 6,
      "subcategory_id": 7,
      "title": "Die Wahrheit über die Lernkurve",
      "slug": "die-wahrheit-lernkurve",
      "description": "Warum die meisten Trader scheitern und wie du die Lernkurve zu deinem Vorteil nutzt",
      "icon": "📈",
      "template_file": "die_wahrheit_lernkurve.html",
      "content_type": "html",
      "external_url": null,
      "is_published": true,
      "is_lead_magnet": false,
      "required_subscription_levels": [
        "elite"
      ],
      "estimated_duration": 30,
      "difficulty_level": "beginner",
      "sort_order": 1
    },
    {
      "id": 15,
      "category_id": 4,
      "subcategory_id": null,
      "title": "Trading mit Risiko",
      "slug": "trading-mit-risiko",
      "description": "Grundlagen des Risikomanagements im Trading",
      "icon": "💰",
      "template_file": null,
      "content_type": "streamlit",
      "external_url": "http://localhost:8501/(0.0)_💰_Trading_mit_Risiko",
      "is_published": true,
      "is_lead_magnet": true,
      "required_subscription_levels": [],
      "estimated_duration": 45,
      "difficulty_level": "beginner",
      "sort_order": 1
    },
    {
      "id": 23,
      "category_id": 6,
      "subcategory_id": 8,
      "title": "Daily Report Card - Das Trading-Tagebuch der Profis",
      "slug": "daily-report-card-lernseite",
      "description": "Lance Breitsteins bewährtes System für exponentiell beschleunigte Trading-Entwicklung. Lerne das mächtigste Tool für strukturierte Selbstverbesserung und gezieltes Deliberate Practice im Trading.",
      "icon": "",
      "template_file": "daily_report_card_lernseite.html",
      "content_type": "html",
      "external_url": null,
      "is_published": true,
      "is_lead_magnet": false,
      "required_subscription_levels": [
        "elite"
      ],
      "estimated_duration": 25,
      "difficulty_level": "intermediate",
      "sort_order": 1
    },
    {
      "id": 25,
      "category_id": 6,
      "subcategory_id": 10,
      "title": "Trading-Playbook System III",
      "slug": "trading-playbook-system-iii",
      "description": "Professionelle Trade-Vorbereitung nach dem \"Mice au Place\" System. Von der Marktanalyse bis zur perfekten Trade-Execution.",
      "icon": "📋",
      "template_file": "trading_playbook_system_iii.html",
      "content_type": "html",
      "external_url": null,
      "is_published": true,
      "is_lead_magnet": false,
      "required_subscription_levels": [
        "elite"
      ],
      "estimated_duration": 60,
      "difficulty_level": "expert",
      "sort_order": 1
    },
    {
      "id": 26,
      "category_id": 3,
      "subcategory_id": 11,
      "title": "Magic Line Strategie",
      "slug": "magic-line",
      "description": "Meistere die Kunst des perfekten Ein- und Ausstiegs - Didis bewährte Verkaufssignale",
      "icon": "🎯",
      "template_file": "magic_line.html",
      "content_type": "html",
      "external_url": null,
      "is_published": true,
      "is_lead_magnet": false,
      "required_subscription_levels": [
        "premium",
        "elite"
      ],
      "estimated_duration": 120,
      "difficulty_level": "advanced",
      "sort_order": 1
    },
    {
      "id": 27,
      "category_id": 8,
      "subcategory_id": null,
      "title": "Avwap Pinch",
      "slug": "avwap-pinch",
      "description": "Interaktives Lernmodul: Avwap Pinch [Vorschlag: technische-analyse]",
      "icon": "📊",
      "template_file": "avwap_pinch.html",
      "content_type": "html",
      "external_url": null,
      "is_published": false,
      "is_lead_magnet": false,
      "required_subscription_levels": [
        "premium",
        "elite"
      ],
      "estimated_duration": 60,
      "difficulty_level": "intermediate",
      "sort_order": 1
    },
    {
      "id": 38,
      "category_id": 1,
      "subcategory_id": null,
      "title": "Position Sizing Kelly",
      "slug": "position-sizing-kelly",
      "description": "Kelly-Kriterium für optimales Position Sizing mit interaktivem Rechner",
      "icon": "🎯",
      "template_file": "Position_Sizing_Kelly.html",
      "content_type": "html",
      "external_url": null,
      "is_published": true,
      "is_lead_magnet": false,
      "required_subscription_levels": [
        "premium",
        "elite"
      ],
      "estimated_duration": 90,
      "difficulty_level": "intermediate",
      "sort_order": 1
    },
    {
      "id": 41,
      "category_id": 8,
      "subcategory_id": null,
      "title": "Defining Trend - Die Kunst der Trend-Erkennung",
      "slug": "defining-trend",
      "description": "Lerne von Lance Breitenstein, wie du Trends richtig definierst, erkennst und nutzt. Mit interaktivem Quiz, Homework Assignments und echten Trading-Beispielen.",
      "icon": "📈",
      "template_file": "defining-trend.html",
      "content_type": "html",
      "external_url": null,
      "is_published": true,
      "is_lead_magnet": false,
      "required_subscription_levels": [
        "premium",
        "elite"
      ],
      "estimated_duration": 45,
      "difficulty_level": "intermediate",
      "sort_order": 1
    },
    {
      "id": 43,
      "category_id": 8,
      "subcategory_id": null,
      "title": "Better Volume Indicator Masterclass",
      "slug": "better-volume-indicator",
      "description": "Erkenne Marktwendepunkte wie die Profis. Lerne die 4 essentiellen Volume-Signale: Climax Up/Down, High Volume Churn und Low Volume. Interaktive 8-Slide-Präsentation mit Quiz und praktischen Beispielen.",
      "icon": "📊",
      "template_file": "better-volume-lernseite.html",
      "content_type": "html",
      "external_url": null,
      "is_published": true,
      "is_lead_magnet": true,
      "required_subscription_levels": [],
      "estimated_duration": 30,
      "difficulty_level": "beginner",
      "sort_order": 1
    },
    {
      "id": 2,
      "category_id": 1,
      "subcategory_id": null,
      "title": "Vermögensaufbau Masterclass: Depots nahe Höchstständen halten",
      "slug": "positioning-risikomanagement",
      "description": "Der Schlüssel zum langfristigen Vermögensaufbau: Wie Sie Ihre Depots nahe an ihren Höchstständen halten und den Compounding-Effekt maximieren",
      "icon": "💼",
      "template_file": "positioning_risikomanagement.html",
      "content_type": "html",
      "external_url": null,
      "is_published": true,
      "is_lead_magnet": false,
      "required_subscription_levels": [
        "premium",
        "elite"
      ],
      "estimated_duration": 60,
      "difficulty_level": "intermediate",
      "sort_order": 2
    },
    {
      "id": 5,
      "category_id": 4,
      "subcategory_id": 5,
      "title": "Kelly-Kriterium: Optimales Position Sizing",
      "slug": "kelly-kriterium",
      "description": "Lerne das Kelly-Kriterium für mathematisch optimales Risikomanagement. Mit interaktivem Rechner und Simulator.",
      "icon": "🎯",
      "template_file": "Position_Sizing_Kelly.html",
      "content_type": "html",
      "external_url": null,
      "is_published": true,
      "is_lead_magnet": false,
      "required_subscription_levels": [
        "premium",
        "elite"
      ],
      "estimated_duration": 90,
      "difficulty_level": "intermediate",
      "sort_order": 2
    },
    {
      "id": 9,
      "category_id": 5,
      "subcategory_id": 6,
      "title": "Trading Mindset Masterclass",
      "slug": "playbook",
      "description": "Warum mehr Informationen nicht die Antwort sind - Eine interaktive Lernreise durch die Trading-Psychologie",
      "icon": "🧠",
      "template_file": "Playbook.html",
      "content_type": "html",
      "external_url": null,
      "is_published": true,
      "is_lead_magnet": false,
      "required_subscription_levels": [
        "premium",
        "elite"
      ],
      "estimated_duration": 45,
      "difficulty_level": "intermediate",
      "sort_order": 2
    },
    {
      "id": 12,
      "category_id": 6,
      "subcategory_id": 7,
      "title": "Finde deinen eigenen Trading-Weg",
      "slug": "finde-deinen-trading-weg",
      "description": "Ein interaktiver Leitfaden zur Entwicklung deines persönlichen Trading-Stils",
      "icon": "🎯",
      "template_file": "finde_deinen_trading_weg.html",
      "content_type": "html",
      "external_url": null,
      "is_published": true,
      "is_lead_magnet": false,
      "required_subscription_levels": [
        "elite"
      ],
      "estimated_duration": 45,
      "difficulty_level": "beginner",
      "sort_order": 2
    },
    {
      "id": 14,
      "category_id": 6,
      "subcategory_id": 8,
      "title": "Trading-Playbook Masterclass",
      "slug": "trading-playbook-masterclass",
      "description": "Systematische Trade-Vorbereitung nach Lance Breitstein - Dein \"Quarterback-Spielbuch\" für erfolgreiches Trading mit interaktivem Playbook-Builder",
      "icon": "📋",
      "template_file": "trading_playbook_masterclass.html",
      "content_type": "html",
      "external_url": null,
      "is_published": true,
      "is_lead_magnet": false,
      "required_subscription_levels": [
        "elite"
      ],
      "estimated_duration": 60,
      "difficulty_level": "advanced",
      "sort_order": 2
    },
    {
      "id": 16,
      "category_id": 4,
      "subcategory_id": null,
      "title": "Marktampel & Allokation",
      "slug": "marktampel-allokation",
      "description": "Professionelle Portfolio-Analyse mit Marktampel-System und optimaler Asset-Allokation",
      "icon": "🚦",
      "template_file": "marktampel_allokation_standalone.html",
      "content_type": "html",
      "external_url": "",
      "is_published": true,
      "is_lead_magnet": true,
      "required_subscription_levels": [],
      "estimated_duration": 45,
      "difficulty_level": "intermediate",
      "sort_order": 2
    },
    {
      "id": 24,
      "category_id": 3,
      "subcategory_id": 4,
      "title": "Volumen-Analyse Grundlagen",
      "slug": "volume-analyse-grundlagen",
      "description": "Lerne die wichtigste Trading-Variable nach Preis und Zeit. Mit Breaking News, Continuation Plays und Kapitulation.",
      "icon": "📊",
      "template_file": "volume-analyse-grundlagen.html",
      "content_type": "html",
      "external_url": null,
      "is_published": true,
      "is_lead_magnet": false,
      "required_subscription_levels": [],
      "estimated_duration": 45,
      "difficulty_level": "beginner",
      "sort_order": 2
    },
    {
      "id": 28,
      "category_id": 8,
      "subcategory_id": null,
      "title": "Börsencrash März 2025",
      "slug": "boersencrash-maerz-2025",
      "description": "Die Vorboten eines historischen Crashs - Eine Fallstudie [Vorschlag: technische-analyse]",
      "icon": "📊",
      "template_file": "boersencrash_maerz_2025.html",
      "content_type": "html",
      "external_url": null,
      "is_published": false,
      "is_lead_magnet": false,
      "required_subscription_levels": [
        "premium",
        "elite"
      ],
      "estimated_duration": 60,
      "difficulty_level": "intermediate",
      "sort_order": 2
    },
    {
      "id": 13,
      "category_id": 2,
      "subcategory_id": null,
      "title": "Darwin Investing: Was ich über Investieren gelernt habe",
      "slug": "darwin-investing",
      "description": "Evolutionäre Prinzipien angewandt auf moderne Investment-Strategien",
      "icon": "🧬",
      "template_file": "darwin_investing.html",
      "content_type": "html",
      "external_url": null,
      "is_published": true,
      "is_lead_magnet": false,
      "required_subscription_levels": [
        "elite"
      ],
      "estimated_duration": 35,
      "difficulty_level": "intermediate",
      "sort_order": 3
    },
    {
      "id": 17,
      "category_id": 5,
      "subcategory_id": null,
      "title": "Die 3 Trader-Archetypen",
      "slug": "drei-trader-archetypen",
      "description": "Verstehe die verschiedenen Trader-Typen und finde deinen Stil",
      "icon": "👥",
      "template_file": null,
      "content_type": "streamlit",
      "external_url": "http://localhost:8501/(0.2)_Die_3_Trader_Archetypen",
      "is_published": true,
      "is_lead_magnet": true,
      "required_subscription_levels": [],
      "estimated_duration": 40,
      "difficulty_level": "beginner",
      "sort_order": 3
    },
    {
      "id": 29,
      "category_id": 8,
      "subcategory_id": null,
      "title": "Ev Calculator",
      "slug": "ev-calculator",
      "description": "Interaktives Lernmodul: Ev Calculator [Vorschlag: technische-analyse]",
      "icon": "📊",
      "template_file": "ev_calculator.html",
      "content_type": "html",
      "external_url": null,
      "is_published": false,
      "is_lead_magnet": false,
      "required_subscription_levels": [
        "premium",
        "elite"
      ],
      "estimated_duration": 60,
      "difficulty_level": "intermediate",
      "sort_order": 3
    },
    {
      "id": 30,
      "category_id": 8,
      "subcategory_id": null,
      "title": "Expected Value (EV)",
      "slug": "expected-value",
      "description": "Interaktives Lernmodul: Expected Value (EV) [Vorschlag: trading-konzepte]",
      "icon": "📊",
      "template_file": "expected_value.html",
      "content_type": "html",
      "external_url": null,
      "is_published": false,
      "is_lead_magnet": false,
      "required_subscription_levels": [
        "premium",
        "elite"
      ],
      "estimated_duration": 60,
      "difficulty_level": "intermediate",
      "sort_order": 4
    },
    {
      "id": 31,
      "category_id": 8,
      "subcategory_id": null,
      "title": "Das Kelly-Kriterium Interaktiv",
      "slug": "kelly-simulator",
      "description": "Interaktives Lernmodul: Kelly-Kriterium Simulator [Vorschlag: risikomanagement]",
      "icon": "⚖️",
      "template_file": "Kelly_Simulator.html",
      "content_type": "html",
      "external_url": null,
      "is_published": false,
      "is_lead_magnet": false,
      "required_subscription_levels": [
        "premium",
        "elite"
      ],
      "estimated_duration": 60,
      "difficulty_level": "intermediate",
      "sort_order": 5
    },
    {
      "id": 40,
      "category_id": 5,
      "subcategory_id": null,
      "title": "Daily Trading Report Card",
      "slug": "daily-report-card",
      "description": "Systematische Selbstreflexion für kontinuierliche Verbesserung",
      "icon": "📋",
      "template_file": "daily_report_card_lernseite.html",
      "content_type": "html",
      "external_url": null,
      "is_published": true,
      "is_lead_magnet": false,
      "required_subscription_levels": [
        "free"
      ],
      "estimated_duration": 45,
      "difficulty_level": "beginner",
      "sort_order": 5
    },
    {
      "id": 42,
      "category_id": 4,
      "subcategory_id": null,
      "title": "Risikomanagement: Dein Ueberlebensguide",
      "slug": "risikomanagement",
      "description": "Lerne die essenziellen Prinzipien des Risikomanagements fuer langfristigen Trading-Erfolg. Verstehe Loss Limits, Position Sizing, die brutale Mathematik des Verlierens und die Psychologie des Risikomanagements.",
      "icon": "warning",
      "template_file": "risikomanagement.html",
      "content_type": "html",
      "external_url": null,
      "is_published": true,
      "is_lead_magnet": true,
      "required_subscription_levels": "[\"free\", \"basic\", \"premium\", \"elite\", \"masterclass\"]",
      "estimated_duration": 45,
      "difficulty_level": "beginner",
      "sort_order": 5
    },
    {
      "id": 32,
      "category_id": 8,
      "subcategory_id": null,
      "title": "Marktampel & Asset Allokation",
      "slug": "marktampel-allokation-1",
      "description": "Interaktives Lernmodul: Marktampel & Asset Allokation [Vorschlag: risikomanagement]",
      "icon": "🚦",
      "template_file": "marktampel_allokation.html",
      "content_type": "html",
      "external_url": null,
      "is_published": false,
      "is_lead_magnet": false,
      "required_subscription_levels": [
        "premium",
        "elite"
      ],
      "estimated_duration": 60,
      "difficulty_level": "intermediate",
      "sort_order": 6
    },
    {
      "id": 33,
      "category_id": 8,
      "subcategory_id": null,
      "title": "Poker Trading Analogie",
      "slug": "poker-cards-comparison",
      "description": "Interaktives Lernmodul: Poker Cards Comparison [Vorschlag: technische-analyse]",
      "icon": "📊",
      "template_file": "poker-cards-comparison.html",
      "content_type": "html",
      "external_url": null,
      "is_published": false,
      "is_lead_magnet": false,
      "required_subscription_levels": [
        "premium",
        "elite"
      ],
      "estimated_duration": 60,
      "difficulty_level": "intermediate",
      "sort_order": 7
    },
    {
      "id": 34,
      "category_id": 8,
      "subcategory_id": null,
      "title": "🎯 ABCD Trade-Grades Calculator | Didis Trading Academy",
      "slug": "position-sizing-abcd-calculator",
      "description": "ABCD Trade-Grades Position Sizing Calculator - Exponentielles Bet-Sizing für Elite-Trader [Vorschlag: risikomanagement]",
      "icon": "⚖️",
      "template_file": "position_sizing_abcd_calculator.html",
      "content_type": "html",
      "external_url": null,
      "is_published": false,
      "is_lead_magnet": false,
      "required_subscription_levels": [
        "premium",
        "elite"
      ],
      "estimated_duration": 60,
      "difficulty_level": "intermediate",
      "sort_order": 8
    },
    {
      "id": 39,
      "category_id": 1,
      "subcategory_id": null,
      "title": "Marktampel Standalone",
      "slug": "marktampel-standalone",
      "description": "Standalone Version des Marktampel-Systems",
      "icon": "🚦",
      "template_file": "marktampel_allokation_standalone.html",
      "content_type": "html",
      "external_url": null,
      "is_published": true,
      "is_lead_magnet": false,
      "required_subscription_levels": [
        "free"
      ],
      "estimated_duration": 30,
      "difficulty_level": "beginner",
      "sort_order": 8
    },
    {
      "id": 35,
      "category_id": 8,
      "subcategory_id": null,
      "title": "📊 Symmetrie im Trading | Didis Trading Academy",
      "slug": "symmetrie-trading",
      "description": "Lerne Symmetrie im Trading - Eine der einfachsten und mächtigsten Heurist\n\niken zur Vorhersage von Kursbewegungen. [Vorschlag: technische-analyse]",
      "icon": "📊",
      "template_file": "symmetrie-trading.html",
      "content_type": "html",
      "external_url": null,
      "is_published": false,
      "is_lead_magnet": false,
      "required_subscription_levels": [
        "premium",
        "elite"
      ],
      "estimated_duration": 60,
      "difficulty_level": "intermediate",
      "sort_order": 9
    },
    {
      "id": 36,
      "category_id": 8,
      "subcategory_id": null,
      "title": "Tirone Levels & Quadrant Lines",
      "slug": "tirone-quadrant-lines",
      "description": "Meistere die wichtigsten TC2000-Indikatoren für präzise Unterstützungs- und Widerstandsanalysen [Vorschlag: technische-analyse]",
      "icon": "📈",
      "template_file": "tirone_quadrant_lines.html",
      "content_type": "html",
      "external_url": null,
      "is_published": false,
      "is_lead_magnet": false,
      "required_subscription_levels": [
        "premium",
        "elite"
      ],
      "estimated_duration": 60,
      "difficulty_level": "intermediate",
      "sort_order": 10
    },
    {
      "id": 37,
      "category_id": 8,
      "subcategory_id": null,
      "title": "Trading Tools",
      "slug": "trading-tools",
      "description": "Interaktives Lernmodul: Trading Tools [Vorschlag: technische-analyse]",
      "icon": "📊",
      "template_file": "trading_tools.html",
      "content_type": "html",
      "external_url": null,
      "is_published": false,
      "is_lead_magnet": false,
      "required_subscription_levels": [
        "premium",
        "elite"
      ],
      "estimated_duration": 60,
      "difficulty_level": "intermediate",
      "sort_order": 11
    },
    {
      "id": 19,
      "category_id": 3,
      "subcategory_id": null,
      "title": "AVWAP Grundlagen",
      "slug": "avwap-grundlagen",
      "description": "Teil I: Die Grundlagen von AVWAP (Advanced Volume Weighted Average Price)",
      "icon": "📊",
      "template_file": null,
      "content_type": "streamlit",
      "external_url": "http://localhost:8501/(2.2)_Teil_I_AVWAP_Grundlagen",
      "is_published": true,
      "is_lead_magnet": false,
      "required_subscription_levels": [
        "premium",
        "elite"
      ],
      "estimated_duration": 75,
      "difficulty_level": "intermediate",
      "sort_order": 14
    },
    {
      "id": 20,
      "category_id": 3,
      "subcategory_id": null,
      "title": "AVWAP Anwenden",
      "slug": "avwap-anwenden",
      "description": "Teil II: AVWAP in der Praxis anwenden",
      "icon": "📊",
      "template_file": null,
      "content_type": "streamlit",
      "external_url": "http://localhost:8501/(2.2.1)_Teil_II_AVWAP_Anwenden",
      "is_published": true,
      "is_lead_magnet": false,
      "required_subscription_levels": [
        "premium",
        "elite"
      ],
      "estimated_duration": 90,
      "difficulty_level": "intermediate",
      "sort_order": 15
    },
    {
      "id": 21,
      "category_id": 3,
      "subcategory_id": null,
      "title": "AVWAP Entry & Exit Techniken",
      "slug": "avwap-entry-exit-techniken",
      "description": "Professionelle Entry- und Exit-Strategien mit AVWAP",
      "icon": "🎯",
      "template_file": null,
      "content_type": "streamlit",
      "external_url": "http://localhost:8501/(2.2.2)_AVWAP_Entry_Exit_Techniken",
      "is_published": true,
      "is_lead_magnet": false,
      "required_subscription_levels": [
        "premium",
        "elite"
      ],
      "estimated_duration": 105,
      "difficulty_level": "advanced",
      "sort_order": 16
    },
    {
      "id": 22,
      "category_id": 5,
      "subcategory_id": null,
      "title": "Trading Psychologie",
      "slug": "trading-psychologie-streamlit",
      "description": "Die psychologischen Aspekte des Tradings (Streamlit Version)",
      "icon": "🧠",
      "template_file": null,
      "content_type": "streamlit",
      "external_url": "http://localhost:8501/(7.0)_🧠_Psychologie",
      "is_published": true,
      "is_lead_magnet": false,
      "required_subscription_levels": [
        "premium",
        "elite"
      ],
      "estimated_duration": 75,
      "difficulty_level": "intermediate",
      "sort_order": 24
    }
  ]
}